pixd.py
pixd-0.0.3.dist-info/DESCRIPTION.rst
pixd-0.0.3.dist-info/METADATA
pixd-0.0.3.dist-info/RECORD
pixd-0.0.3.dist-info/WHEEL
pixd-0.0.3.dist-info/metadata.json
pixd-0.0.3.dist-info/top_level.txt
pixd-0.0.3.dist-info/zip-safe
