Metadata-Version: 2.0
Name: pixd
Version: 0.0.3
Summary: A tool for visualizing binary data using a colour palette
Home-page: https://github.com/moreati/python-pixd
Author: Alex Willmer
Author-email: alex@moreati.org.uk
License: MIT license
Keywords: hexdump
Platform: UNKNOWN
Classifier: Development Status :: 2 - Pre-Alpha
Classifier: Environment :: Console
Classifier: License :: OSI Approved :: MIT License
Classifier: Natural Language :: English
Classifier: Operating System :: OS Independent
Classifier: Programming Language :: Python :: 2
Classifier: Programming Language :: Python :: 2.7
